sopel_modules.cryptocurrency-1.2.2-py3.9-nspkg.pth
sopel_modules/cryptocurrency/__init__.py
sopel_modules/cryptocurrency/cryptocurrency.py
sopel_modules_cryptocurrency-1.2.2.dist-info/licenses/LICENSE
sopel_modules_cryptocurrency-1.2.2.dist-info/METADATA
sopel_modules_cryptocurrency-1.2.2.dist-info/WHEEL
sopel_modules_cryptocurrency-1.2.2.dist-info/namespace_packages.txt
sopel_modules_cryptocurrency-1.2.2.dist-info/top_level.txt
sopel_modules_cryptocurrency-1.2.2.dist-info/RECORD
