Metadata-Version: 2.4
Name: sopel_modules.cryptocurrency
Version: 1.2.2
Summary: Cryptocurrency Lookup
Home-page: http://github.com/rustybower/sopel-cryptocurrency
Author: Rusty Bower
Author-email: rusty@rustybower.com
License: MIT License
License-File: LICENSE
Requires-Dist: arrow
Requires-Dist: datetime
Requires-Dist: requests
Requires-Dist: sopel
Dynamic: author
Dynamic: author-email
Dynamic: description
Dynamic: description-content-type
Dynamic: home-page
Dynamic: license
Dynamic: license-file
Dynamic: requires-dist
Dynamic: summary
